studenttestpackage/__init__.py
studenttestpackage/myfunctions.py
studenttestpackage-1.0.dist-info/licenses/license.txt
studenttestpackage-1.0.dist-info/METADATA
studenttestpackage-1.0.dist-info/WHEEL
studenttestpackage-1.0.dist-info/top_level.txt
studenttestpackage-1.0.dist-info/RECORD
