Metadata-Version: 2.4
Name: studenttestpackage
Version: 1.0
Summary: Test python packae for students
Home-page: https://github.com/smaurice101/transactionalmachinelearning
Author: Sebastian Maurice
Author-email: sebastian.maurice@otics.ca
License: MIT License
Keywords: python, data science, machine learning ,artificial intelligence,predictive analytics,advanced analytics
License-File: license.txt
Requires-Dist: numpy>=1.18.1
Requires-Dist: pandas>=0.25.3
Dynamic: author
Dynamic: author-email
Dynamic: description
Dynamic: description-content-type
Dynamic: home-page
Dynamic: keywords
Dynamic: license
Dynamic: license-file
Dynamic: requires-dist
Dynamic: summary
